json_as_db/__init__.py
json_as_db/_utils/__init__.py
json_as_db/_utils/decorater.py
json_as_db/constants.py
json_as_db/core/__init__.py
json_as_db/core/_formatting.py
json_as_db/core/database.py
json_as_db/core/matcher.py
json_as_db/core/operator.py
json_as_db/statics.py
json_as_db-0.2.4.dist-info/METADATA
json_as_db-0.2.4.dist-info/WHEEL
json_as_db-0.2.4.dist-info/LICENSE
json_as_db-0.2.4.dist-info/RECORD
