Metadata-Version: 2.1
Name: json-as-db
Version: 0.2.4
Summary: Using JSON as very lightweight database
License: MIT
Keywords: json,lightweight,database,odm
Author: Joonas
Author-email: joonas.yoon@gmail.com
Maintainer: Joonas
Maintainer-email: joonas.yoon@gmail.com
Requires-Python: >=3.7,<4.0
Classifier: Development Status :: 4 - Beta
Classifier: License :: OSI Approved :: MIT License
Classifier: Operating System :: OS Independent
Classifier: Programming Language :: Python :: 3
Classifier: Programming Language :: Python :: 3.7
Classifier: Programming Language :: Python :: 3.8
Classifier: Programming Language :: Python :: 3.9
Classifier: Programming Language :: Python :: 3.10
Classifier: Programming Language :: Python :: 3.11
Classifier: Programming Language :: Python :: 3
Classifier: Topic :: Database
Classifier: Topic :: System :: Filesystems
Requires-Dist: aiofiles (>=22.1.0)
Requires-Dist: shortuuid (>=1.0.11)
Project-URL: changelog, https://github.com/joonas-yoon/json-as-db/blob/master/CHANGELOG.md
Project-URL: documentation, https://json-as-db.readthedocs.io/
Project-URL: homepage, https://www.joonas.io/json-as-db
Project-URL: repository, https://github.com/joonas-yoon/json-as-db
